economy/__init__.py
economy/economy.py
pythoneconomy-0.0.6.dist-info/LICENSE
pythoneconomy-0.0.6.dist-info/METADATA
pythoneconomy-0.0.6.dist-info/WHEEL
pythoneconomy-0.0.6.dist-info/top_level.txt
pythoneconomy-0.0.6.dist-info/RECORD
