Metadata-Version: 2.1
Name: pythoneconomy
Version: 0.0.6
Summary: A Easier way to make a Economic System
Home-page: https://github.com/ErrorThree/Python-Economy
Author: ErrorTwo
Author-email: errortwoo@gmail.com
License: UNKNOWN
Project-URL: Bug Tracker, https://github.com/ErrorThree/Python-Economy/issues
Platform: UNKNOWN
Classifier: Programming Language :: Python :: 3
Classifier: License :: OSI Approved :: MIT License
Classifier: Operating System :: OS Independent
Requires-Python: >=3.7
License-File: LICENSE
